lumina_widgets-0.1.0.dist-info/licenses/LICENSE
luminawidgets/__init__.py
luminawidgets/types/__init__.py
luminawidgets/types/enums.py
luminawidgets/types/node.py
luminawidgets/types/pos.py
luminawidgets/widgets/bases/__init__.py
luminawidgets/widgets/bases/_connection.py
luminawidgets/widgets/bases/_node.py
luminawidgets/widgets/bases/_port.py
luminawidgets/widgets/bases/_scene.py
luminawidgets/widgets/bases/_view.py
luminawidgets/widgets/nodes/basics.py
lumina_widgets-0.1.0.dist-info/METADATA
lumina_widgets-0.1.0.dist-info/WHEEL
lumina_widgets-0.1.0.dist-info/top_level.txt
lumina_widgets-0.1.0.dist-info/RECORD
