Metadata-Version: 2.4
Name: lumina-widgets
Version: 0.1.0
Summary: Powerful and beautiful widgets based on PySide6
Requires-Python: >=3.12
License-File: LICENSE
Requires-Dist: pydantic>=2.11.4
Requires-Dist: pyside6>=6.9.0
Dynamic: license-file
